collin/__init__.py
collin-0.0.1.dist-info/METADATA
collin-0.0.1.dist-info/WHEEL
collin-0.0.1.dist-info/top_level.txt
collin-0.0.1.dist-info/RECORD
