Metadata-Version: 2.1
Name: collin
Version: 0.0.1
Summary: Install collinizda
Author: CollinIzDa
Author-email: <info@collinizda.de>
Keywords: python,collinizda,CollinIzDa
Classifier: Development Status :: 1 - Planning
Classifier: Intended Audience :: Developers
Classifier: Programming Language :: Python :: 3
Classifier: Operating System :: Unix
Classifier: Operating System :: MacOS :: MacOS X
Classifier: Operating System :: Microsoft :: Windows
